LICENSE
weighbridge_agent/__init__.py
weighbridge_agent/__main__.py
weighbridge_agent-0.1.0.dist-info/LICENSE
weighbridge_agent-0.1.0.dist-info/METADATA
weighbridge_agent-0.1.0.dist-info/WHEEL
weighbridge_agent-0.1.0.dist-info/entry_points.txt
weighbridge_agent-0.1.0.dist-info/RECORD
